cli.py
models.py
tests.py
tracko-0.1.0.dist-info/AUTHORS.rst
tracko-0.1.0.dist-info/LICENCE
tracko-0.1.0.dist-info/METADATA
tracko-0.1.0.dist-info/WHEEL
tracko-0.1.0.dist-info/entry_points.txt
tracko-0.1.0.dist-info/top_level.txt
tracko-0.1.0.dist-info/RECORD
