Metadata-Version: 2.1
Name: tracko
Version: 0.1.0
Summary: Track your series!
Home-page: https://github.com/revisto/tracko2
Author: Alireza Shabani
Author-email: walt.shabani@gmail.com
License: LGPL-2.1-or-later
Project-URL: Issue Tracker, https://github.com/revisto/tracko2/issues
Platform: UNKNOWN
Classifier: Development Status :: 5 - Production/Stable
Classifier: Intended Audience :: Developers
Classifier: License :: OSI Approved :: GNU Lesser General Public License v2 or later (LGPLv2+)
Classifier: Programming Language :: Python
Classifier: Programming Language :: Python :: 3
Classifier: Programming Language :: Python :: 3 :: Only
Classifier: Programming Language :: Python :: 3.6
Classifier: Programming Language :: Python :: 3.7
Classifier: Programming Language :: Python :: 3.8
Classifier: Programming Language :: Python :: 3.9
Classifier: Topic :: Utilities
Requires-Python: >=3.0
Requires-Dist: questionary
Requires-Dist: rich
Requires-Dist: click
Requires-Dist: prompt-toolkit
Requires-Dist: requests
Requires-Dist: validator-collection
